pylb/__init__.py
pylb/parts/code_diff_check.py
pylb/parts/dir_id.py
pylb/parts/error_message.py
pylb/parts/import_core.py
pylb/parts/path_utils.py
pylb-0.0.2.dist-info/DESCRIPTION.rst
pylb-0.0.2.dist-info/METADATA
pylb-0.0.2.dist-info/RECORD
pylb-0.0.2.dist-info/WHEEL
pylb-0.0.2.dist-info/metadata.json
pylb-0.0.2.dist-info/top_level.txt
